zmq_plugin/__init__.py
zmq_plugin/hub.py
zmq_plugin/plugin.py
zmq_plugin/schema.py
zmq_plugin/bin/__init__.py
zmq_plugin/bin/hub.py
zmq_plugin/bin/monitor.py
zmq_plugin/bin/plugin.py
zmq_plugin/examples/__init__.py
zmq_plugin/examples/demo.py
zmq_plugin/examples/hub.py
zmq_plugin-0.2.post14.dist-info/DESCRIPTION.rst
zmq_plugin-0.2.post14.dist-info/METADATA
zmq_plugin-0.2.post14.dist-info/RECORD
zmq_plugin-0.2.post14.dist-info/WHEEL
zmq_plugin-0.2.post14.dist-info/metadata.json
zmq_plugin-0.2.post14.dist-info/pbr.json
zmq_plugin-0.2.post14.dist-info/top_level.txt
