Metadata-Version: 2.0
Name: zmq-plugin
Version: 0.2.post14
Summary: A spoke-hub plugin framework, using 0MQ backend.
Home-page: https://github.com/wheeler-microfluidics/zmq-plugin
Author: Christian Fobel
Author-email: christian@fobel.net
License: LGPLv2.1
Platform: UNKNOWN
Requires-Dist: arrow (>=0.7.0)
Requires-Dist: jsonschema
Requires-Dist: pandas
Requires-Dist: pyyaml
Requires-Dist: pyzmq
